statannotations/Annotation.py
statannotations/Annotator.py
statannotations/PValueFormat.py
statannotations/_GroupsPositions.py
statannotations/_Plotter.py
statannotations/__init__.py
statannotations/_version.py
statannotations/format_annotations.py
statannotations/utils.py
statannotations/stats/ComparisonsCorrection.py
statannotations/stats/StatResult.py
statannotations/stats/StatTest.py
statannotations/stats/__init__.py
statannotations/stats/test.py
statannotations/stats/utils.py
remi_statannotations_fork-0.6.0.dist-info/LICENSE
remi_statannotations_fork-0.6.0.dist-info/METADATA
remi_statannotations_fork-0.6.0.dist-info/WHEEL
remi_statannotations_fork-0.6.0.dist-info/top_level.txt
remi_statannotations_fork-0.6.0.dist-info/RECORD
