Metadata-Version: 2.1
Name: remi-statannotations-fork
Version: 0.6.0
Summary: add statistical significance or custom annotations on seaborn plots. Based on statannot 0.2.3
Home-page: https://github.com/trevismd/statannotations
Maintainer: Florian Charlier
Maintainer-email: trevis@cascliniques.be
License: MIT License
Platform: UNKNOWN
Classifier: Programming Language :: Python :: 3
Classifier: License :: OSI Approved :: MIT License
Classifier: Operating System :: OS Independent
Requires-Python: >=3.6
License-File: LICENSE
Requires-Dist: matplotlib
Requires-Dist: numpy
Requires-Dist: pandas
Requires-Dist: scipy
Requires-Dist: seaborn (<0.13.0)
